{
  "_comment": "Attach this policy to the IAM user used by GitHub Actions (AWS_ACCESS_KEY_ID / AWS_SECRET_ACCESS_KEY). Replace ACCOUNT_ID and REGION. The same credentials are also used on the Lightsail instance for ECR login, S3 backups, and SES email.",

  "Version": "2012-10-17",
  "Statement": [
    {
      "Sid": "ECRAuth",
      "Effect": "Allow",
      "Action": ["ecr:GetAuthorizationToken"],
      "Resource": "*"
    },
    {
      "Sid": "ECRPushPull",
      "Effect": "Allow",
      "Action": [
        "ecr:BatchCheckLayerAvailability",
        "ecr:GetDownloadUrlForLayer",
        "ecr:BatchGetImage",
        "ecr:PutImage",
        "ecr:InitiateLayerUpload",
        "ecr:UploadLayerPart",
        "ecr:CompleteLayerUpload",
        "ecr:DescribeRepositories",
        "ecr:CreateRepository"
      ],
      "Resource": [
        "arn:aws:ecr:REGION:ACCOUNT_ID:repository/triage-insight-api",
        "arn:aws:ecr:REGION:ACCOUNT_ID:repository/triage-insight-worker",
        "arn:aws:ecr:REGION:ACCOUNT_ID:repository/triage-insight-web"
      ]
    },
    {
      "Sid": "CloudFrontInvalidation",
      "Effect": "Allow",
      "Action": [
        "cloudfront:CreateInvalidation",
        "cloudfront:GetDistribution",
        "cloudfront:ListDistributions"
      ],
      "Resource": "*"
    },
    {
      "Sid": "S3AppUploadsAndBackups",
      "Effect": "Allow",
      "Action": [
        "s3:PutObject",
        "s3:GetObject",
        "s3:DeleteObject",
        "s3:ListBucket"
      ],
      "Resource": [
        "arn:aws:s3:::triage-insight-uploads-prod",
        "arn:aws:s3:::triage-insight-uploads-prod/*"
      ]
    },
    {
      "Sid": "SESEmail",
      "Effect": "Allow",
      "Action": [
        "ses:SendEmail",
        "ses:SendRawEmail"
      ],
      "Resource": "*"
    }
  ]
}
